h26x_extractor/__init__.py
h26x_extractor/__main__.py
h26x_extractor/h26x_parser.py
h26x_extractor/nalutypes.py
h26x_extractor-0.11.0.dist-info/licenses/LICENSE.md
h26x_extractor-0.11.0.dist-info/WHEEL
h26x_extractor-0.11.0.dist-info/entry_points.txt
h26x_extractor-0.11.0.dist-info/METADATA
h26x_extractor-0.11.0.dist-info/RECORD
