Metadata-Version: 2.4
Name: h26x-extractor
Version: 0.11.0
Summary: Extract NAL units from H.264 bitstreams
Keywords: video,h264
Author: Werner Robitza
Author-email: Werner Robitza <werner.robitza@gmail.com>
License-Expression: MIT
License-File: LICENSE.md
Classifier: Development Status :: 4 - Beta
Classifier: Intended Audience :: Developers
Classifier: Topic :: Multimedia :: Video
Classifier: Natural Language :: English
Classifier: Programming Language :: Python :: 3
Classifier: Programming Language :: Python :: 3.9
Classifier: Programming Language :: Python :: 3.10
Classifier: Programming Language :: Python :: 3.11
Classifier: Programming Language :: Python :: 3.12
Classifier: Programming Language :: Python :: 3.13
Classifier: Programming Language :: Python :: 3.14
Requires-Dist: docopt
Requires-Dist: tabulate
Requires-Dist: bitstring
Requires-Python: >=3.9
Project-URL: Homepage, https://github.com/slhck/h26x-extractor
Project-URL: Repository, https://github.com/slhck/h26x-extractor
